authress_sdk/VERSION
authress_sdk/__init__.py
authress_sdk/authress_client.py
authress_sdk/http_client.py
authress_sdk/rest.py
authress_sdk/api/__init__.py
authress_sdk/api/access_records_api.py
authress_sdk/api/accounts_api.py
authress_sdk/api/resource_permissions_api.py
authress_sdk/api/service_client_token_provider.py
authress_sdk/api/service_clients_api.py
authress_sdk/api/token_verifier.py
authress_sdk/api/user_permissions_api.py
authress_sdk/models/__init__.py
authress_sdk/models/access_record.py
authress_sdk/models/access_record_account.py
authress_sdk/models/access_record_collection.py
authress_sdk/models/access_record_group.py
authress_sdk/models/access_record_resource.py
authress_sdk/models/access_record_statement.py
authress_sdk/models/access_record_user.py
authress_sdk/models/account.py
authress_sdk/models/account_collection.py
authress_sdk/models/claim_request.py
authress_sdk/models/claim_response.py
authress_sdk/models/client.py
authress_sdk/models/client_access_key.py
authress_sdk/models/client_collection.py
authress_sdk/models/client_options.py
authress_sdk/models/identity.py
authress_sdk/models/identity_collection.py
authress_sdk/models/identity_request.py
authress_sdk/models/permission_object.py
authress_sdk/models/resource_permission.py
authress_sdk/models/resource_permission_collection.py
authress_sdk/models/resource_permission_object.py
authress_sdk/models/user_permissions.py
authress_sdk/models/user_resources.py
authress_sdk-2.0.34.data/data/VERSION
test/__init__.py
test/test_service_client_token_provider.py
test/test_token_verifier.py
authress_sdk-2.0.34.dist-info/METADATA
authress_sdk-2.0.34.dist-info/WHEEL
authress_sdk-2.0.34.dist-info/top_level.txt
authress_sdk-2.0.34.dist-info/RECORD
