Metadata-Version: 2.1
Name: authress-sdk
Version: 2.0.34
Summary: Authress SDK for authorization as a service and interact with the Authress API.
Home-page: https://github.com/Authress/authress-sdk.py.git
Author: Rhosys Developers
Author-email: developers@authress.io
License: Apache-2.0
Keywords: Authorization as a service,Security,authorization,authorization as a service,authentication,user authentication,Authress,Authress client,access management,access management as a service,user security,oso,polar,open source policy engine,embedded authorization,batteries included authorization
Requires-Dist: urllib3 >=1.15
Requires-Dist: six >=1.10
Requires-Dist: certifi
Requires-Dist: python-dateutil
Requires-Dist: PyJWT >=2.0.0
Requires-Dist: cryptography >=2.9.2
Requires-Dist: authress >=3.0.29
